COPYING
MANIFEST.in
README.md
setup.cfg
setup.py
tfcv/__init__.py
tfcv/aggregator.py
tfcv/loss.py
tfcv/metric.py
tfcv/predict.py
tfcv/util.py
tfcv.egg-info/PKG-INFO
tfcv.egg-info/SOURCES.txt
tfcv.egg-info/dependency_links.txt
tfcv.egg-info/requires.txt
tfcv.egg-info/top_level.txt
tfcv/model/__init__.py
tfcv/model/aspp.py
tfcv/model/config.py
tfcv/model/decode.py
tfcv/model/densenet.py
tfcv/model/erfnet.py
tfcv/model/esanet.py
tfcv/model/hrnet.py
tfcv/model/mscale.py
tfcv/model/ocr.py
tfcv/model/pspnet.py
tfcv/model/res2net.py
tfcv/model/resnet.py
tfcv/model/senet.py
tfcv/model/shortcut.py
tfcv/model/transformer.py
tfcv/model/unet.py
tfcv/model/upernet.py
tfcv/model/util.py
tfcv/model/vit.py
tfcv/model/pretrained/__init__.py
tfcv/model/pretrained/weights.py
tfcv/model/pretrained/deepmotionairesearch/__init__.py
tfcv/model/pretrained/deepmotionairesearch/densenet161_denseaspp_cityscapes.py
tfcv/model/pretrained/hrnet/COPYING
tfcv/model/pretrained/hrnet/__init__.py
tfcv/model/pretrained/hrnet/hrnet_v2_w48_cityscapes.py
tfcv/model/pretrained/hrnet/hrnet_v2_w48_ocr_cityscapes.py
tfcv/model/pretrained/hrnet/util.py
tfcv/model/pretrained/nvidia/COPYING
tfcv/model/pretrained/nvidia/__init__.py
tfcv/model/pretrained/nvidia/hrnet_v2_w48_ocr_mscale_cityscapes.py
tfcv/model/pretrained/openmmlab/COPYING
tfcv/model/pretrained/openmmlab/__init__.py
tfcv/model/pretrained/openmmlab/upernet_vitb_ade20k.py
tfcv/model/pretrained/tensorfloworg/__init__.py
tfcv/model/pretrained/tensorfloworg/resnet_v1b_101_imagenet.py
tfcv/model/pretrained/tensorfloworg/resnet_v1b_152_imagenet.py
tfcv/model/pretrained/tensorfloworg/resnet_v1b_50_imagenet.py
tfcv/model/pretrained/tensorfloworg/resnet_v1b_x_imagenet.py
tfcv/model/pretrained/tuinicr/COPYING
tfcv/model/pretrained/tuinicr/__init__.py
tfcv/model/pretrained/tuinicr/esanet_resnet_v1b_34_nbt1d_nyuv2.py
tfcv/model/pretrained/vainf/COPYING
tfcv/model/pretrained/vainf/__init__.py
tfcv/model/pretrained/vainf/deeplabv3plus_resnet101_v1b_cityscapes.py
tfcv/model/pretrained/vladkryvoruchko/COPYING
tfcv/model/pretrained/vladkryvoruchko/__init__.py
